alteon_sdk-0.15b1.data/data/sdk_requirements.txt
radware/alteon/__init__.py
radware/alteon/client.py
radware/alteon/exceptions.py
radware/alteon/api/__init__.py
radware/alteon/api/config.py
radware/alteon/api/mgmt.py
radware/alteon/beans/AgAccessHttpsCfgCertsTable.py
radware/alteon/beans/AgAccessNewCfgEnhUserRealTable.py
radware/alteon/beans/AgAccessNewCfgSshPubKeyTable.py
radware/alteon/beans/AgAccessNewHttpsCfgGroupsTable.py
radware/alteon/beans/AgAccessNewHttpsCfgIntermCertsTable.py
radware/alteon/beans/AgAccessUserEnhRealsTable.py
radware/alteon/beans/AgAccessUserNewCfgTable.py
radware/alteon/beans/AgApplyTable.py
radware/alteon/beans/AgCfgDumpTable.py
radware/alteon/beans/AgCfgSecurityPortTable.py
radware/alteon/beans/AgDiffTable.py
radware/alteon/beans/AgDosPortStatsTable.py
radware/alteon/beans/AgFileErrorTable.py
radware/alteon/beans/AgFileTable.py
radware/alteon/beans/AgImageAdcTable.py
radware/alteon/beans/AgImageVxTable.py
radware/alteon/beans/AgLastSyncInfoTable.py
radware/alteon/beans/AgLicenseCapacityInfoTable.py
radware/alteon/beans/AgLicenseInfoTable.py
radware/alteon/beans/AgNewCfgHcTcpPortTable.py
radware/alteon/beans/AgNewCfgMgmtNet6Table.py
radware/alteon/beans/AgNewCfgMgmtNetTable.py
radware/alteon/beans/AgNewCfgPgrpMatchTable.py
radware/alteon/beans/AgNewCfgPortAccessTable.py
radware/alteon/beans/AgNewCfgTrapHostTable.py
radware/alteon/beans/AgNewCfgVLANAccessTable.py
radware/alteon/beans/AgPortNewCfgTable.py
radware/alteon/beans/AgPortOperTable.py
radware/alteon/beans/AgSaveTable.py
radware/alteon/beans/AgSecIpAclOperDstTable.py
radware/alteon/beans/AgSecIpAclOperSrcTable.py
radware/alteon/beans/AgSecurityIpAclStatsTable.py
radware/alteon/beans/AgSecurityIpDstAclStatsTable.py
radware/alteon/beans/AgSecurityPgrpStatsTable.py
radware/alteon/beans/AgSecurityUbStatsTable.py
radware/alteon/beans/AgSnmpErrorTbTable.py
radware/alteon/beans/AgSysPeerNewCfgTable.py
radware/alteon/beans/AgSyslogMsgTable.py
radware/alteon/beans/AgSyslogSavedMsgTable.py
alteon_sdk-0.15b1.dist-info/LICENSE
alteon_sdk-0.15b1.dist-info/METADATA
alteon_sdk-0.15b1.dist-info/WHEEL
alteon_sdk-0.15b1.dist-info/top_level.txt
alteon_sdk-0.15b1.dist-info/RECORD
