Metadata-Version: 2.1
Name: alteon-sdk
Version: 0.15b1
Summary: Python Alteon SDK
Home-page: https://pypi.python.org/pypi/alteon-sdk
Author: Leon Meguira
Author-email: leonm@radware.com
License: Apache 2.0
Keywords: radware,sdk,api,configurators,beans
Platform: UNKNOWN
Classifier: Development Status :: 4 - Beta
Classifier: License :: OSI Approved :: Apache Software License
Classifier: Operating System :: OS Independent
Classifier: Programming Language :: Python :: 3.6
Classifier: Programming Language :: Python :: 3.7
Classifier: Programming Language :: Python :: 3.8
Classifier: Intended Audience :: System Administrators
Classifier: Intended Audience :: Developers
Requires-Python: ~=3.6
License-File: LICENSE
Requires-Dist: typing-inspect >0.3
Requires-Dist: urllib3 >=1.23
Requires-Dist: radware-sdk-common ==0.4b32
